py_scraper/__init__.py
py_scraper/py-scraper.py
py_scraper/scrap.py
py_scraper-0.0.0.dist-info/METADATA
py_scraper-0.0.0.dist-info/WHEEL
py_scraper-0.0.0.dist-info/top_level.txt
py_scraper-0.0.0.dist-info/RECORD
