Metadata-Version: 2.1
Name: py-scraper
Version: 0.0.0
Summary: Proxy scraper using requests and bs4.
Home-page: https://github.com/Chibraax/
Author: Chibraax
Author-email: alexandrelesieur@hotmail.fr
License: UNKNOWN
Platform: UNKNOWN
Requires-Dist: bs4
Requires-Dist: requests
